README.txt
setup.cfg
setup.py
docs/AUTHORS.txt
docs/CHANGES.txt
docs/INSTALL.txt
docs/LICENSE.txt
p4a/__init__.py
p4a.calendar.egg-info/PKG-INFO
p4a.calendar.egg-info/SOURCES.txt
p4a.calendar.egg-info/dependency_links.txt
p4a.calendar.egg-info/entry_points.txt
p4a.calendar.egg-info/namespace_packages.txt
p4a.calendar.egg-info/not-zip-safe
p4a.calendar.egg-info/requires.txt
p4a.calendar.egg-info/top_level.txt
p4a/calendar/TODO.txt
p4a/calendar/__init__.py
p4a/calendar/configure.zcml
p4a/calendar/interfaces.py
p4a/calendar/tests.py
p4a/calendar/browser/__init__.py
p4a/calendar/browser/config.py
p4a/calendar/browser/configure.zcml
p4a/calendar/browser/events.pt
p4a/calendar/browser/events.py
p4a/calendar/browser/month.pt
p4a/calendar/browser/month.py
p4a/calendar/browser/tests.py
p4a/calendar/browser/resources/anchor-position.js
p4a/calendar/browser/resources/calendar.css
p4a/calendar/browser/resources/calendar.js
p4a/calendar/browser/resources/event-icon.gif
p4a/calendar/browser/resources/popup-window.js
p4a/calendar/locales/p4a.calendar.pot
p4a/calendar/locales/de/LC_MESSAGES/p4a.calendar.po
p4a/calendar/locales/el/LC_MESSAGES/p4a.calendar.po
p4a/calendar/locales/en/LC_MESSAGES/p4a.calendar.po
p4a/calendar/locales/es/LC_MESSAGES/p4a.calendar.po
p4a/calendar/locales/fi/LC_MESSAGES/p4a.calendar.po
p4a/calendar/locales/fr/LC_MESSAGES/p4a.calendar.po
p4a/calendar/locales/nl/LC_MESSAGES/p4a.calendar.po
p4a/calendar/locales/no/LC_MESSAGES/p4a.calendar.po