Metadata-Version: 1.0
Name: p4a.calendar
Version: 1.2
Summary: Plone4Artists calendar abstraction library
Home-page: http://pypi.python.org/pypi/p4a.calendar
Author: Rocky Burt
Author-email: rocky@serverzen.com
License: GPL
Keywords: Plone4Artists
Platform: UNKNOWN
Classifier: Framework :: Zope3
Classifier: Programming Language :: Python
Classifier: License :: OSI Approved :: GNU General Public License (GPL)
Classifier: Topic :: Software Development :: Libraries :: Python Modules
